{
  "fetched_at": "2026-04-10T19:29:58Z",
  "normalized_payload": {
    "avm_confidence": 86,
    "avm_fsd": null,
    "avm_high": 2835043,
    "avm_low": 2138716,
    "avm_value": 2486880
  },
  "raw_payload": {
    "property": [
      {
        "address": {
          "country": "US",
          "countrySubd": "NJ",
          "line1": "308 3RD AVE",
          "line2": "BRADLEY BEACH, NJ 07720",
          "locality": "BRADLEY BEACH",
          "matchCode": "ExaStr",
          "oneLine": "308 3RD AVE, BRADLEY BEACH, NJ 07720",
          "postal1": "07720",
          "postal2": "1264"
        },
        "area": {
          "blockNum": "63",
          "countrysecsubd": "Monmouth",
          "countyuse1": "2",
          "muncode": "MO",
          "munname": "MONMOUTH",
          "taxcodearea": "08"
        },
        "avm": {
          "AVMChange": {
            "avmamountchange": 25492,
            "avmlastmonthvalue": 2461388,
            "avmpercentchange": 1
          },
          "amount": {
            "high": 2835043,
            "low": 2138716,
            "scr": 86,
            "value": 2486880,
            "valueRange": 348163
          },
          "calculations": {
            "perSizeUnit": 680.0,
            "rangePctOfValue": 28.0,
            "ratioTaxAmt": 140.64,
            "ratioTaxValue": 1.0
          },
          "condition": {
            "avmexcellenthigh": 2905919.08,
            "avmexcellentlow": 2192183.9,
            "avmgoodhigh": 2835043.0,
            "avmgoodlow": 2138716.0,
            "avmpoorhigh": 2693290.85,
            "avmpoorlow": 2031780.2
          },
          "eventDate": "2026-03-25"
        },
        "building": {
          "construction": {
            "condition": "GOOD",
            "roofShape": "GABLE",
            "roofcover": "OTHER (NOT CLASSIFIED)",
            "wallType": "ALUMINUM/VINYL"
          },
          "interior": {
            "bsmtsize": 780,
            "fplccount": 1
          },
          "parking": {
            "garagetype": "Garage, Detached",
            "prkgSize": 360,
            "prkgSpaces": "1",
            "prkgType": "Garage, Detached"
          },
          "rooms": {
            "bathsfull": 3,
            "bathstotal": 3.0,
            "beds": 3,
            "roomsTotal": 7
          },
          "size": {
            "bldgsize": 3657,
            "grosssizeadjusted": 3657,
            "livingsize": 3657,
            "sizeInd": "LIVING SQFT",
            "universalsize": 3657
          },
          "summary": {
            "archStyle": "COLONIAL",
            "bldgsNum": 1,
            "levels": 2,
            "quality": "NP",
            "unitsCount": "1",
            "yearbuilteffective": 1924
          }
        },
        "identifier": {
          "Id": 42837102,
          "apn": "08-00063-0000-00017",
          "apnOrig": "08-00063-0000-00017",
          "attomId": 42837102,
          "fips": "34025"
        },
        "location": {
          "accuracy": "Rooftop",
          "distance": 0.0,
          "geoIdV4": {
            "CO": "55b1095f659ca5ad6f1b6d3b683d5673",
            "CS": "16dc81b3fc0dee1144f8aa5de26c4701",
            "DB": "bfea690b7241bbdcc51682fae6f5d7cd, 1e3d1025bdcaaa58a0b29cbc7bf7e5e7, 0c681e7e925f43acf1c9667deda1c5c1",
            "PL": "5a456aa9b27c49f0683ac49724f58756",
            "SB": "de7618c8f103aec825226d889bfbdfe8, f75571e64593fd61dce03f6c9b87358b, a16cbf0dfb7aadac47d791f6bd3fba26",
            "ZI": "2795e990df349e8fe4b408e9236e35b2"
          },
          "geoid": "CO34025, CS3406970, DB3402130, PL3406970, ZI07720",
          "latitude": "40.199383",
          "longitude": "-74.012794"
        },
        "lot": {
          "depth": 150,
          "frontage": 50,
          "lotnum": "17",
          "lotsize1": 0.172,
          "lotsize2": 7501,
          "poolind": "YES"
        },
        "summary": {
          "absenteeInd": "OWNER OCCUPIED",
          "propIndicator": "10",
          "propLandUse": "SFR",
          "propclass": "Single Family Residence / Townhouse",
          "propertyType": "SINGLE FAMILY RESIDENCE",
          "propsubtype": "Residential",
          "proptype": "SFR",
          "yearbuilt": 1924
        },
        "utilities": {
          "coolingtype": "YES",
          "heatingtype": "FORCED AIR WITH AIR CONDITIONING",
          "sewertype": "YES",
          "watertype": "YES - TYPE UNKNOWN"
        },
        "vintage": {
          "lastModified": "2026-04-08",
          "pubDate": "2026-04-08"
        }
      }
    ],
    "status": {
      "attomId": 42837102,
      "code": 0,
      "msg": "SuccessWithResult",
      "page": 1,
      "pagesize": 10,
      "responseDateTime": "2026-04-10T19:29:58.137Z",
      "total": 1,
      "transactionID": "015680834b6aec5a449e4498150b3163",
      "version": "1.0.0"
    }
  }
}